CryptographyMethods/CryptographyMethods.py
CryptographyMethods/__init__.py
CryptographyMethods-0.1.1.dist-info/METADATA
CryptographyMethods-0.1.1.dist-info/WHEEL
CryptographyMethods-0.1.1.dist-info/top_level.txt
CryptographyMethods-0.1.1.dist-info/RECORD
