Metadata-Version: 2.1
Name: CryptographyMethods
Version: 0.1.1
Summary: An implementation of cryptography used for keeping secrets within Lab-93.
Author-email: Hunter Dale <guyyatsu@gmail.com>
Project-URL: Homepage, https://github.com/guyyatsu/CryptographyMethods
Project-URL: Bug Tracker, https://github.com/guyyatsu/CryptographyMethods/issues
Classifier: Programming Language :: Python :: 3
Classifier: License :: OSI Approved :: MIT License
Classifier: Operating System :: OS Independent
Requires-Python: >=3.11
Requires-Dist: cryptography
